adder/half_adder.v
module half_adder
(
	input wire in_1,
	input wire in_2,
	output wire sum,
	output wire count
);
assign {count,sum} = in_1+in_2;
endmodule

adder/full_adder.v
module full_adder
(
	input wire in_1,
	input wire in_2,
	input wire cin,
	output wire sum,
	output wire count
);
wire h0_sum;
wire h0_count;
wire h1_count;

half_adder half_adder_inst0
(
	.in_1 (in_1),
	.in_2 (in_2),
	.sum (h0_sum),
	.count (h0_count)
);
half_adder half_adder_inst1
(
	.in_1 (cin),
	.in_2 (h0_sum),
	.sum (sum),
	.count (h1_count)
);

assign count = (h0_count||h1_count);
endmodule

adder/tb_full_adder.v
`timescale 1ns/1ns
module tb_full_adder();

reg  in_1;
reg  in_2;
reg  cin;

initial
	begin 
		in_1 <= 1'b0;
		in_2 <= 1'b0;
		cin <= 1'b0;
	end
initial
	begin
	$timeformat(-9,0,"ns",6);
	$monitor("time %t: in_1=%b,in_2=%b,cin=%b,sum=%b,count=%b",$time,in_1,in_2,cin,sum,count);
	#1000
		$stop;
	end
initial
begin
   $dumpfile("test.vcd");
   $dumpvars(0,tb_full_adder);
end
always #10 in_1 <= {$random} % 2;
always #10 in_2 <= {$random} % 2;
always #10 cin <= {$random} % 2;

full_adder full_adder_inst
(
	.in_1 (in_1),
	.in_2 (in_2),
	.cin  (cin),
	.sum  (sum),
	.count (count)
);
endmodule

adder/test.vcd
$date
	Mon Oct 16 21:18:50 2023
$end
$version
	Icarus Verilog
$end
$timescale
	1ns
$end
$scope module tb_full_adder $end
$var wire 1 ! sum $end
$var wire 1 " count $end
$var reg 1 # cin $end
$var reg 1 $ in_1 $end
$var reg 1 % in_2 $end
$scope module full_adder_inst $end
$var wire 1 # cin $end
$var wire 1 " count $end
$var wire 1 $ in_1 $end
$var wire 1 % in_2 $end
$var wire 1 ! sum $end
$var wire 1 & h1_count $end
$var wire 1 ' h0_sum $end
$var wire 1 ( h0_count $end
$scope module half_adder_inst0 $end
$var wire 1 $ in_1 $end
$var wire 1 % in_2 $end
$var wire 1 ' sum $end
$var wire 1 ( count $end
$upscope $end
$scope module half_adder_inst1 $end
$var wire 1 # in_1 $end
$var wire 1 ' in_2 $end
$var wire 1 ! sum $end
$var wire 1 & count $end
$upscope $end
$upscope $end
$upscope $end
$enddefinitions $end
#0
$dumpvars
0(
0'
0&
0%
0$
0#
0"
0!
$end
#10
1"
1&
1'
1#
1%
#20
1!
0&
0'
1(
1$
#30
0!
1&
1"
1'
0(
0%
#60
0"
1!
0&
0#
1%
0$
#70
0!
1"
0'
1(
1$
#80
1!
0"
1'
0(
0%
#90
1%
0$
#100
1"
0'
1(
1#
1$
#110
0"
1'
0(
0#
0%
#120
0'
1#
0$
#130
1"
0!
1&
1'
1%
#140
1!
0&
0'
1(
1$
#150
0"
0(
0%
0$
#160
1"
0!
1(
0#
1%
1$
#170
0"
0(
0%
0$
#180
1!
1'
1%
#190
1"
0!
1&
1#
#200
0"
0&
0'
0#
0%
#210
1!
1#
#220
1"
1(
1%
1$
#230
0"
1'
0(
0#
0%
#240
1"
0'
1(
1#
1%
#250
0"
0(
0%
0$
#260
1"
0!
1&
1'
1$
#280
0&
0'
1(
0#
1%
#300
0"
0(
0%
0$
#310
1"
1(
1%
1$
#320
1&
1"
1'
0(
1#
0$
#330
1!
0&
0'
1(
1$
#340
0!
1&
1"
1'
0(
0$
#350
0"
1!
0&
0#
0%
1$
#360
0!
0'
0$
#370
1!
1#
#380
1"
1(
1%
1$
#390
0!
1&
1"
1'
0(
0%
#400
0"
1!
0&
0#
#410
0!
1"
0'
1(
1%
#420
1!
1#
#430
0"
1'
0(
0#
0%
#440
1%
0$
#450
0'
1#
0%
#460
1'
0#
1$
#480
1%
0$
#500
1"
0'
1(
1#
1$
#510
0!
0#
#520
0"
1!
0(
1#
0%
0$
#540
1'
0#
1$
#550
1"
0!
1&
1#
1%
0$
#560
0"
0&
0'
0#
0%
#570
1"
1(
1%
1$
#580
0"
1!
0(
1#
0%
0$
#600
0!
0#
#610
1"
1&
1'
1#
1$
#620
0"
1!
0&
0#
#630
0'
1#
0$
#640
0!
0#
#650
1"
1&
1'
1#
1%
#660
0%
1$
#670
0&
0'
1(
0#
1%
#680
1&
1"
1'
0(
1#
0$
#690
1!
0&
0'
1(
1$
#700
0!
1&
1"
1'
0(
0$
#710
0"
0&
0'
0#
0%
#720
1"
1&
1'
1#
1%
#730
0"
1!
0&
0'
0%
#770
1"
0!
1(
0#
1%
1$
#780
0"
1!
0(
1#
0%
0$
#800
0!
0#
#810
1!
1'
1%
#820
0'
1#
0%
#830
1"
0!
1&
1'
1$
#840
1!
0&
0'
1(
1%
#850
0!
1&
1"
1'
0(
0$
#860
0"
1!
0&
0#
0%
1$
#880
0!
1"
0'
1(
1%
#890
1!
0"
1'
0(
0$
#910
0!
1"
0'
1(
1$
#920
1&
1"
1'
0(
1#
0%
#930
0"
1!
0&
0'
0$
#940
0!
0#
#950
1"
1!
1(
1#
1%
1$
#960
0!
0#
#970
1!
1#
#980
0"
0!
0(
0#
0%
0$
